README.md
pyproject.toml
setup.cfg
setup.py
elisctl/__init__.py
elisctl/argument.py
elisctl/common.py
elisctl/configure.py
elisctl/connector.py
elisctl/main.py
elisctl/option.py
elisctl/queue.py
elisctl/user.py
elisctl/user_assignment.py
elisctl/webhook.py
elisctl/workspace.py
elisctl.egg-info/PKG-INFO
elisctl.egg-info/SOURCES.txt
elisctl.egg-info/dependency_links.txt
elisctl.egg-info/entry_points.txt
elisctl.egg-info/not-zip-safe
elisctl.egg-info/requires.txt
elisctl.egg-info/top_level.txt
elisctl/document/__init__.py
elisctl/document/extract_data.py
elisctl/lib/__init__.py
elisctl/lib/api_client.py
elisctl/schema/__init__.py
elisctl/schema/commands.py
elisctl/schema/upload.py
elisctl/schema/xlsx.py
elisctl/schema/transform/__init__.py
elisctl/schema/transform/commands.py
elisctl/tools/__init__.py
elisctl/tools/compare.py
elisctl/tools/csv_to_options.py
elisctl/tools/xls_to_csv.py