Metadata-Version: 2.1
Name: elisctl
Version: 2.9.1
Summary: Command line interface for controlling the Rossum platform
Home-page: https://developers.rossum.ai/
Author: Rossum developers
Author-email: support@rossum.ai
License: MIT
Project-URL: Source, https://github.com/rossumai/elisctl
Project-URL: Tracker, https://github.com/rossumai/elisctl/issues
Platform: UNKNOWN
Classifier: Development Status :: 4 - Beta
Classifier: Intended Audience :: Developers
Classifier: Intended Audience :: System Administrators
Classifier: License :: OSI Approved :: MIT License
Classifier: Natural Language :: English
Classifier: Operating System :: OS Independent
Classifier: Programming Language :: Python
Classifier: Programming Language :: Python :: 3
Classifier: Programming Language :: Python :: 3.6
Classifier: Programming Language :: Python :: 3.7
Requires-Python: >=3.6
